.build
MANIFEST.in
lyrics
lyricwiki.py
setup.py
lyricwiki.egg-info/PKG-INFO
lyricwiki.egg-info/SOURCES.txt
lyricwiki.egg-info/dependency_links.txt
lyricwiki.egg-info/top_level.txt