Metadata-Version: 1.0
Name: lyricwiki
Version: 0.1.18
Summary: Download lyrics from LyricWiki
Home-page: UNKNOWN
Author: Amr Hassan
Author-email: amr.hassan@gmail.com
License: gpl3
Platform: UNKNOWN
